kwparse/__init__.py
kwparse/__main__.py
kwparse/core/__init__.py
kwparse/tests/__init__.py
kwparse/tests/test_1984.py
kwparse-0.0.0.dev0.dist-info/licenses/LICENSE.txt
kwparse-0.0.0.dev0.dist-info/METADATA
kwparse-0.0.0.dev0.dist-info/WHEEL
kwparse-0.0.0.dev0.dist-info/top_level.txt
kwparse-0.0.0.dev0.dist-info/RECORD
