Metadata-Version: 2.4
Name: kwparse
Version: 0.0.0.dev0
Summary: kwparse
Author-email: Johannes <johannes.programming@gmail.com>
License: The MIT License (MIT)
Project-URL: Download, https://pypi.org/project/kwparse/#files
Project-URL: Index, https://pypi.org/project/kwparse/
Project-URL: Source, https://github.com/johannes-programming/kwparse/
Classifier: Development Status :: 1 - Planning
Classifier: License :: OSI Approved :: MIT License
Classifier: Natural Language :: English
Classifier: Operating System :: OS Independent
Classifier: Programming Language :: Python
Classifier: Programming Language :: Python :: 3
Classifier: Programming Language :: Python :: 3 :: Only
Classifier: Typing :: Typed
Requires-Python: >=3.11
License-File: LICENSE.txt
Dynamic: license-file
